README.md
setup.cfg
setup.py
decile_distil.egg-info/PKG-INFO
decile_distil.egg-info/SOURCES.txt
decile_distil.egg-info/dependency_links.txt
decile_distil.egg-info/requires.txt
decile_distil.egg-info/top_level.txt
distil/__init__.py
distil/active_learning_strategies/__init__.py
distil/active_learning_strategies/adversarial_bim.py
distil/active_learning_strategies/adversarial_deepfool.py
distil/active_learning_strategies/badge.py
distil/active_learning_strategies/bayesian_active_learning_disagreement_dropout.py
distil/active_learning_strategies/core_set.py
distil/active_learning_strategies/craig_active.py
distil/active_learning_strategies/entropy_sampling.py
distil/active_learning_strategies/entropy_sampling_dropout.py
distil/active_learning_strategies/fass.py
distil/active_learning_strategies/glister.py
distil/active_learning_strategies/gradmatch_active.py
distil/active_learning_strategies/kmeans_sampling.py
distil/active_learning_strategies/least_confidence.py
distil/active_learning_strategies/least_confidence_dropout.py
distil/active_learning_strategies/margin_sampling.py
distil/active_learning_strategies/margin_sampling_dropout.py
distil/active_learning_strategies/random_sampling.py
distil/active_learning_strategies/strategy.py
distil/active_learning_strategies/submod_sampling.py
distil/utils/__init__.py
distil/utils/calculate_class_budgets.py
distil/utils/config_helper.py
distil/utils/data_handler.py
distil/utils/dataset.py
distil/utils/disparity_functions.py
distil/utils/dpp.py
distil/utils/gradmatch_solvers.py
distil/utils/similarity_mat.py
distil/utils/submodular.py
distil/utils/supervised_strategy_wrappers.py
distil/utils/train_helper.py
distil/utils/models/__init__.py
distil/utils/models/cifar10net.py
distil/utils/models/densenet.py
distil/utils/models/dla.py
distil/utils/models/dla_simple.py
distil/utils/models/dpn.py
distil/utils/models/efficientnet.py
distil/utils/models/googlenet.py
distil/utils/models/lenet.py
distil/utils/models/logreg_net.py
distil/utils/models/mnist_net.py
distil/utils/models/mobilenet.py
distil/utils/models/mobilenetv2.py
distil/utils/models/mobilenetv2tf.py
distil/utils/models/pnasnet.py
